histomics_stream/__init__.py
histomics_stream/codecs.py
histomics_stream/configure.py
histomics_stream/pytorch.py
histomics_stream/tensorflow.py
histomics_stream-2.5.3.dist-info/entry_points.txt
histomics_stream-2.5.3.dist-info/LICENSE.txt
histomics_stream-2.5.3.dist-info/WHEEL
histomics_stream-2.5.3.dist-info/METADATA
histomics_stream-2.5.3.dist-info/RECORD
