Metadata-Version: 2.1
Name: histomics_stream
Version: 2.5.3
Summary: Whole-slide image streamer for machine learning frameworks.
Keywords: tensorflow,torch,whole slide image,stream,machine learning
Author-email: "Lee A. Newberg" <lee.newberg@kitware.com>
Maintainer-email: "Lee A. Newberg" <lee.newberg@kitware.com>
Requires-Python: >=3.6
Classifier: License :: OSI Approved :: Apache Software License
Requires-Dist: imagecodecs
Requires-Dist: itk
Requires-Dist: numcodecs
Requires-Dist: numpy
Requires-Dist: scipy
Requires-Dist: tensorflow<3.0.0 ; extra == "tensorflow"
Requires-Dist: keras ; extra == "tensorflow"
Requires-Dist: torch<2.0.0 ; extra == "torch"
Requires-Dist: zarr ; extra == "zarr"
Project-URL: Source, https://github.com/DigitalSlideArchive/HistomicsStream
Provides-Extra: tensorflow
Provides-Extra: torch
Provides-Extra: zarr
